LICENSE.md
README.md
setup.py
correlade/correlade.c
correlade/correlade.pyx
correlade.egg-info/PKG-INFO
correlade.egg-info/SOURCES.txt
correlade.egg-info/dependency_links.txt
correlade.egg-info/not-zip-safe
correlade.egg-info/requires.txt
correlade.egg-info/top_level.txt