Metadata-Version: 1.1
Name: correlade
Version: 1.0.1
Summary: Distance correlation matrix and graph for a given set of variables
Home-page: https://github.com/colemai/correlade
Author: Ian Coleman
Author-email: colemai@tcd.ie
License: UNKNOWN
Keywords: correlation data-science pandas
Platform: Linux
Classifier: Development Status :: 4 - Beta
Classifier: Environment :: Console
Classifier: Intended Audience :: Developers
Classifier: Intended Audience :: Science/Research
Classifier: Operating System :: POSIX :: Linux
Classifier: Programming Language :: Cython
Classifier: Programming Language :: Python
Classifier: Programming Language :: Python :: 2
Classifier: Programming Language :: Python :: 2.7
Classifier: Programming Language :: Python :: 3
Classifier: Programming Language :: Python :: 3.4
Classifier: Topic :: Scientific/Engineering
Classifier: Topic :: Scientific/Engineering :: Mathematics
Classifier: Topic :: Software Development :: Libraries
Classifier: Topic :: Software Development :: Libraries :: Python Modules
Provides: setup_template_cython
